gitreload/__init__.py
gitreload/config.py
gitreload/processing.py
gitreload/tests/__init__.py
gitreload/tests/base.py
gitreload/tests/data/gr.env.bad.json
gitreload/tests/data/gr.env.json
gitreload/tests/test_config.py
gitreload/tests/test_processing.py
gitreload/tests/test_web.py
gitreload/web.py
gitreload-0.2.5.dist-info/entry_points.txt
gitreload-0.2.5.dist-info/LICENSE
gitreload-0.2.5.dist-info/WHEEL
gitreload-0.2.5.dist-info/METADATA
gitreload-0.2.5.dist-info/RECORD
