Metadata-Version: 2.1
Name: gitreload
Version: 0.2.5
Summary: Service for triggering edX course imports from Github webhooks
Home-page: https://github.com/mitodl/gitreload
License: AGPL-3.0
Author: MIT Open Learning
Author-email: mitx-devops@mit.edu
Requires-Python: >=3.5,<4.0
Classifier: Development Status :: 3 - Alpha
Classifier: Environment :: Web Environment
Classifier: Framework :: Flask
Classifier: Intended Audience :: Developers
Classifier: License :: OSI Approved :: GNU Affero General Public License v3
Classifier: Operating System :: OS Independent
Classifier: Programming Language :: Python
Classifier: Programming Language :: Python :: 3
Classifier: Programming Language :: Python :: 3.5
Classifier: Programming Language :: Python :: 3.6
Classifier: Programming Language :: Python :: 3.7
Classifier: Programming Language :: Python :: 3.8
Classifier: Topic :: Education
Requires-Dist: flask (>=1.1.2,<2.0.0)
Requires-Dist: gitpython (>=3.1.3,<4.0.0)
Requires-Dist: gunicorn (>=20.0.4,<21.0.0)
Project-URL: Repository, https://github.com/mitodl/gitreload
